{
    "assets": {
        "shaders": {
            "basic": {
                "vbasic": "assets/shaders/basic.vert",
                "fbasic": "assets/shaders/basic.frag"
            }
        },
        "models": {
            "building": "assets/models/sponza/sponza.obj",
            "camera": "assets/models/camera/camera.obj"
        },
        "prefabs": {
            "structures": {
                "filepath": "assets/prefabs/structures.json",
                "targeted_prototypes": [
                    "building"
                ]
            },
            "objects": {
                "filepath": "assets/prefabs/objects.json",
                "targeted_prototypes": [
                    "camera"
                ]
            }
        }
    },
    "entities": {
        "normals": {
            "sponza": {
                "prefab": "structures",
                "prototype": "building",
                "options": {
                    "scale": {"x": 0.01,"y": 0.01,"z": 0.01},
                    "position": {"x": 0, "y": 0, "z": 0}
                }
            }
        },
        "cameras": {
            "scene_camera": {
                "prefab": "objects",
                "prototype": "camera",
                "options": {
                    "position": {"x": 8, "y": 6, "z": 3},
                    "type": "perspective",
                    "isActive": true
                }
            }
        }
    }
}